<?xml version="1.0" encoding="UTF-8"?>
<diagnostic><item><date>Thu, 11 Dec 2014 14:48:33 GMT</date><PageRank>1</PageRank><AlexaReach>3116061</AlexaReach><AlexaBackLink>3</AlexaBackLink><AlexaRank>2951008</AlexaRank><GoogleBackLink>0</GoogleBackLink><GoogleIndexed>0</GoogleIndexed><BingBackLink>0</BingBackLink><BingIndexed>0</BingIndexed></item><item><date>Fri, 12 Dec 2014 12:37:15 GMT</date><PageRank>1</PageRank><AlexaReach>3105730</AlexaReach><AlexaBackLink>3</AlexaBackLink><AlexaRank>2931886</AlexaRank><GoogleBackLink>0</GoogleBackLink><GoogleIndexed>0</GoogleIndexed><BingBackLink>0</BingBackLink><BingIndexed>0</BingIndexed></item><item><date>Sat, 13 Dec 2014 12:37:34 GMT</date><PageRank>1</PageRank><AlexaReach>3093659</AlexaReach><AlexaBackLink>3</AlexaBackLink><AlexaRank>2751879</AlexaRank><GoogleBackLink>0</GoogleBackLink><GoogleIndexed>0</GoogleIndexed><BingBackLink>0</BingBackLink><BingIndexed>0</BingIndexed></item><item><date>Mon, 15 Dec 2014 01:20:38 GMT</date><PageRank>1</PageRank><AlexaReach>3035868</AlexaReach><AlexaBackLink>3</AlexaBackLink><AlexaRank>2582569</AlexaRank><GoogleBackLink>0</GoogleBackLink><GoogleIndexed>0</GoogleIndexed><BingBackLink>0</BingBackLink><BingIndexed>0</BingIndexed></item><item><date>Tue, 16 Dec 2014 04:06:32 GMT</date><PageRank>1</PageRank><AlexaReach>2972354</AlexaReach><AlexaBackLink>3</AlexaBackLink><AlexaRank>2494000</AlexaRank><GoogleBackLink>0</GoogleBackLink><GoogleIndexed>0</GoogleIndexed><BingBackLink>0</BingBackLink><BingIndexed>0</BingIndexed></item><item><date>Fri, 19 Dec 2014 00:36:45 GMT</date><PageRank>1</PageRank><AlexaReach>2953677</AlexaReach><AlexaBackLink>3</AlexaBackLink><AlexaRank>2471055</AlexaRank><GoogleBackLink>0</GoogleBackLink><GoogleIndexed>0</GoogleIndexed><BingBackLink>0</BingBackLink><BingIndexed>0</BingIndexed></item><item><date>Sat, 20 Dec 2014 08:35:14 GMT</date><PageRank>1</PageRank><AlexaReach>2965412</AlexaReach><AlexaBackLink>3</AlexaBackLink><AlexaRank>2476457</AlexaRank><GoogleBackLink>0</GoogleBackLink><GoogleIndexed>0</GoogleIndexed><BingBackLink>0</BingBackLink><BingIndexed>0</BingIndexed></item><item><date>Sat, 20 Dec 2014 12:26:17 GMT</date><PageRank>1</PageRank><AlexaReach>2965412</AlexaReach><AlexaBackLink>3</AlexaBackLink><AlexaRank>2476457</AlexaRank><GoogleBackLink>0</GoogleBackLink><GoogleIndexed>0</GoogleIndexed><BingBackLink>0</BingBackLink><BingIndexed>0</BingIndexed></item><item><date>Mon, 22 Dec 2014 00:09:33 GMT</date><PageRank>1</PageRank><AlexaReach>2910829</AlexaReach><AlexaBackLink>3</AlexaBackLink><AlexaRank>2420439</AlexaRank><GoogleBackLink>0</GoogleBackLink><GoogleIndexed>0</GoogleIndexed><BingBackLink>0</BingBackLink><BingIndexed>0</BingIndexed></item><item><date>Mon, 22 Dec 2014 13:24:25 GMT</date><PageRank>1</PageRank><AlexaReach>2902446</AlexaReach><AlexaBackLink>3</AlexaBackLink><AlexaRank>2415404</AlexaRank><GoogleBackLink>0</GoogleBackLink><GoogleIndexed>0</GoogleIndexed><BingBackLink>0</BingBackLink><BingIndexed>0</BingIndexed></item><item><date>Tue, 23 Dec 2014 12:08:41 GMT</date><PageRank>1</PageRank><AlexaReach>2893507</AlexaReach><AlexaBackLink>3</AlexaBackLink><AlexaRank>2410112</AlexaRank><GoogleBackLink>0</GoogleBackLink><GoogleIndexed>0</GoogleIndexed><BingBackLink>0</BingBackLink><BingIndexed>0</BingIndexed></item><item><date>Thu, 25 Dec 2014 00:06:38 GMT</date><PageRank>1</PageRank><AlexaReach>2893507</AlexaReach><AlexaBackLink>3</AlexaBackLink><AlexaRank>2410112</AlexaRank><GoogleBackLink>0</GoogleBackLink><GoogleIndexed>0</GoogleIndexed><BingBackLink>0</BingBackLink><BingIndexed>0</BingIndexed></item><item><date>Thu, 25 Dec 2014 12:08:35 GMT</date><PageRank>1</PageRank><AlexaReach>2893507</AlexaReach><AlexaBackLink>3</AlexaBackLink><AlexaRank>2410112</AlexaRank><GoogleBackLink>0</GoogleBackLink><GoogleIndexed>0</GoogleIndexed><BingBackLink>0</BingBackLink><BingIndexed>0</BingIndexed></item><item><date>Fri, 26 Dec 2014 18:29:35 GMT</date><PageRank>1</PageRank><AlexaReach>2725660</AlexaReach><AlexaBackLink>3</AlexaBackLink><AlexaRank>2295114</AlexaRank><GoogleBackLink>0</GoogleBackLink><GoogleIndexed>0</GoogleIndexed><BingBackLink>0</BingBackLink><BingIndexed>0</BingIndexed></item></diagnostic>
